latex2pydata/__init__.py
latex2pydata/err.py
latex2pydata/fmtversion.py
latex2pydata/loading.py
latex2pydata/schema.py
latex2pydata/util.py
latex2pydata/version.py
latex2pydata-0.5.0.dist-info/CHANGELOG.md
latex2pydata-0.5.0.dist-info/LICENSE.txt
latex2pydata-0.5.0.dist-info/METADATA
latex2pydata-0.5.0.dist-info/WHEEL
latex2pydata-0.5.0.dist-info/top_level.txt
latex2pydata-0.5.0.dist-info/RECORD
