Metadata-Version: 2.2
Name: latex2pydata
Version: 0.5.0
Summary: Load data from LaTeX in Python literal format
Author-email: "Geoffrey M. Poore" <gpoore@gmail.com>
License: BSD 3-Clause License
Project-URL: homepage, https://github.com/gpoore/latex2pydata/tree/main/python
Project-URL: repository, https://github.com/gpoore/latex2pydata
Project-URL: changelog, https://github.com/gpoore/latex2pydata/blob/main/python/CHANGELOG.md
Keywords: deserialization,LaTeX,Python literal format
Classifier: Development Status :: 4 - Beta
Classifier: Programming Language :: Python
Classifier: Intended Audience :: Developers
Classifier: Intended Audience :: Education
Classifier: Intended Audience :: Science/Research
Classifier: License :: OSI Approved :: BSD License
Classifier: Operating System :: OS Independent
Classifier: Topic :: File Formats
Classifier: Topic :: Software Development :: Libraries
Requires-Python: >=3.8
License-File: LICENSE.txt
License-File: CHANGELOG.md
